README.md
setup.cfg
setup.py
OnionSVG/__init__.py
OnionSVG/onion.py
OnionSVG.egg-info/PKG-INFO
OnionSVG.egg-info/SOURCES.txt
OnionSVG.egg-info/dependency_links.txt
OnionSVG.egg-info/requires.txt
OnionSVG.egg-info/top_level.txt