Metadata-Version: 1.1
Name: OnionSVG
Version: 0.1.1
Summary: Peel your SVG files with Python
Home-page: https://github.com/ybnd/OnionSVG
Author: ybnd
Author-email: ybnd@tuta.io
License: UNKNOWN
Download-URL: https://github.com/ybnd/OnionSVG/archive/v0.1.1.tar.gz
Platform: UNKNOWN
